BANOS/BANOS.py
BANOS/__init__.py
BANOS-0.1.5.dist-info/METADATA
BANOS-0.1.5.dist-info/WHEEL
BANOS-0.1.5.dist-info/top_level.txt
BANOS-0.1.5.dist-info/RECORD
