Metadata-Version: 2.1
Name: BANOS
Version: 0.1.5
Summary: Set of metrics to assess behavior annotations of videos.
Home-page: https://github.com/BelloneLab/BANOS
Author: Benoit Girad and Giuseppe Chindemi
Author-email: benoit.girard@unige.ch
License: MIT
Project-URL: Source, https://github.com/BelloneLab/BANOS
Project-URL: Tracker, https://github.com/BelloneLab/BANOS/issues
Keywords: behavior analysis,annotation,video,metrics
Requires-Python: >=3.7
Requires-Dist: pandas >=1.0.5
Requires-Dist: numpy >=1.18.5
Requires-Dist: matplotlib >=3.2.2
Requires-Dist: seaborn >=0.10.1
